<?xml version="1.0" encoding="utf-8" ?>
<dwsync>
<file name="Timezone.php" server="hq-dev-01//var/www/YIITEMPLATE/" local="130124425950000000" remote="130428341200000000" />
<file name="AccessLevel.php" server="hq-dev-01//var/www/YIITEMPLATE/" local="130124425950000000" remote="130428341200000000" />
<file name="QuickAdd.php" server="hq-dev-01//var/www/YIITEMPLATE/" local="130124425950000000" remote="130428341200000000" />
<file name="Hidden.php" server="hq-dev-01//var/www/YIITEMPLATE/" local="130124425950000000" remote="130428341200000000" />
<file name="SendEventNotifications.php" server="hq-dev-01//var/www/YIITEMPLATE/" local="130124425950000000" remote="130428341200000000" />
<file name="WebContent.php" server="hq-dev-01//var/www/YIITEMPLATE/" local="130124425950000000" remote="130428341200000000" />
<file name="Selected.php" server="hq-dev-01//var/www/YIITEMPLATE/" local="130124425950000000" remote="130428341200000000" />
<file name="Link.php" server="hq-dev-01//var/www/YIITEMPLATE/" local="130124425950000000" remote="130428341200000000" />
<file name="Color.php" server="hq-dev-01//var/www/YIITEMPLATE/" local="130124425950000000" remote="130428341200000000" />
</dwsync>